openmeteo_requests/Client.py
openmeteo_requests/__init__.py
openmeteo_requests-1.0.0.dist-info/METADATA
openmeteo_requests-1.0.0.dist-info/WHEEL
openmeteo_requests-1.0.0.dist-info/licenses/LICENSE
openmeteo_requests-1.0.0.dist-info/RECORD
