Metadata-Version: 2.1
Name: openmeteo_requests
Version: 1.0.0
Summary: Open-Meteo Python Library
Project-URL: Documentation, https://github.com/open-meteo/python-requests/tree/main#readme
Project-URL: Source, https://github.com/open-meteo/python-requests
Project-URL: Tracker, https://github.com/open-meteo/python-requests/issues
Author-email: Patrick Zippenfenig <info@open-meteo.com>
License-File: LICENSE
Classifier: Development Status :: 3 - Alpha
Classifier: Intended Audience :: Developers
Classifier: License :: OSI Approved :: MIT License
Classifier: Programming Language :: Python :: 3 :: Only
Classifier: Programming Language :: Python :: 3.8
Classifier: Programming Language :: Python :: 3.9
Classifier: Programming Language :: Python :: 3.10
Classifier: Programming Language :: Python :: 3.11
Requires-Python: >=3.8.1
Requires-Dist: openmeteo-sdk
Requires-Dist: requests
Provides-Extra: spark
Requires-Dist: pyspark>=3.0.0; extra == 'spark'
Provides-Extra: test
Requires-Dist: bandit[toml]==1.7.5; extra == 'test'
Requires-Dist: black==23.9.1; extra == 'test'
Requires-Dist: check-manifest==0.49; extra == 'test'
Requires-Dist: flake8; extra == 'test'
Requires-Dist: flake8-bugbear==23.9.16; extra == 'test'
Requires-Dist: flake8-docstrings; extra == 'test'
Requires-Dist: flake8-formatter-junit-xml; extra == 'test'
Requires-Dist: flake8-pyproject; extra == 'test'
Requires-Dist: pre-commit==3.5.0; extra == 'test'
Requires-Dist: pylint-junit; extra == 'test'
Requires-Dist: pylint==3.0.1; extra == 'test'
Requires-Dist: pytest-asyncio; extra == 'test'
Requires-Dist: pytest-cov==4.1.0; extra == 'test'
Requires-Dist: pytest-github-actions-annotate-failures; extra == 'test'
Requires-Dist: pytest-mock<3.11.2; extra == 'test'
Requires-Dist: pytest-runner; extra == 'test'
Requires-Dist: pytest==7.4.2; extra == 'test'
Requires-Dist: shellcheck-py==0.9.0.6; extra == 'test'
